bulk_update_or_create/__init__.py
bulk_update_or_create/apps.py
bulk_update_or_create/query.py
django_bulk_update_or_create-0.3.0.dist-info/LICENSE
django_bulk_update_or_create-0.3.0.dist-info/METADATA
django_bulk_update_or_create-0.3.0.dist-info/WHEEL
django_bulk_update_or_create-0.3.0.dist-info/top_level.txt
django_bulk_update_or_create-0.3.0.dist-info/RECORD
